{"cameraMode":{"drawMode":0,"name":"Shaded","section":"Shading Mode"},"sceneLighting":true,"audioPlay":false,"sceneViewState":{"m_AlwaysRefresh":false,"showFog":true,"showSkybox":true,"showFlares":true,"showImageEffects":true,"showParticleSystems":true,"showVisualEffectGraphs":true,"m_FxEnabled":true},"in2DMode":false,"pivot":{"x":1099.3984375,"y":1280.8243408203125,"z":44.10099792480469},"rotation":{"x":0.019497519358992578,"y":0.011109594255685807,"z":0.00021506355551537126,"w":-0.999755322933197},"size":608.9544677734375,"orthographic":false}